nostr/__init__.py
nostr/_version.py
nostr/bech32.py
nostr/delegation.py
nostr/event.py
nostr/filter.py
nostr/key.py
nostr/message_pool.py
nostr/message_type.py
nostr/pow.py
nostr/relay.py
nostr/relay_manager.py
nostr/request.py
nostr/subscription.py
nostr_r3drun3-0.1.5.dist-info/LICENSE
nostr_r3drun3-0.1.5.dist-info/METADATA
nostr_r3drun3-0.1.5.dist-info/WHEEL
nostr_r3drun3-0.1.5.dist-info/top_level.txt
nostr_r3drun3-0.1.5.dist-info/RECORD
