Metadata-Version: 2.1
Name: nostr-r3drun3
Version: 0.1.5
Summary: A Python library for making Nostr clients
Author-email: Jeff Thibault <jdthibault2@gmail.com>
License: MIT License
Project-URL: Homepage, https://github.com/jeffthibault/python-nostr
Classifier: Operating System :: POSIX :: Linux
Classifier: Operating System :: Microsoft :: Windows
Classifier: Operating System :: MacOS :: MacOS X
Requires-Python: >3.6.0
License-File: LICENSE
Requires-Dist: cffi (>=1.15.0)
Requires-Dist: cryptography (>=37.0.4)
Requires-Dist: pycparser (>=2.21)
Requires-Dist: python-socks (>=2.1.1)
Requires-Dist: secp256k1 (>=0.14.0)
Requires-Dist: websocket-client (>=1.3.3)
Provides-Extra: test
Requires-Dist: pytest (>=7.2.0) ; extra == 'test'
Requires-Dist: pytest-cov[all] ; extra == 'test'
